idem_gitlab/conf.py
idem_gitlab/version.py
idem_gitlab/acct/gitlab/init.py
idem_gitlab/acct/gitlab/login.py
idem_gitlab/acct/gitlab/oauth.py
idem_gitlab/autogen/gitlab/functions.py
idem_gitlab/autogen/gitlab/init.py
idem_gitlab/autogen/gitlab/param.py
idem_gitlab/autogen/gitlab/plugin.py
idem_gitlab/autogen/gitlab/resource.py
idem_gitlab/autogen/gitlab/template.py
idem_gitlab/autogen/gitlab/hooks/post_gen_project.py
idem_gitlab/cloudspec/create/tests.py
idem_gitlab/cloudspec/create/tool.py
idem_gitlab/exec/gitlab/avatar.py
idem_gitlab/exec/gitlab/group.py
idem_gitlab/exec/gitlab/impersonation_token.py
idem_gitlab/exec/gitlab/init.py
idem_gitlab/exec/gitlab/metadata.py
idem_gitlab/exec/gitlab/namespace.py
idem_gitlab/exec/gitlab/personal_access_token.py
idem_gitlab/exec/gitlab/project.py
idem_gitlab/exec/gitlab/runner.py
idem_gitlab/exec/gitlab/user.py
idem_gitlab/exec/gitlab/version.py
idem_gitlab/exec/gitlab/group/init.py
idem_gitlab/exec/gitlab/group/member.py
idem_gitlab/exec/gitlab/group/variable.py
idem_gitlab/exec/gitlab/project/branch.py
idem_gitlab/exec/gitlab/project/commit.py
idem_gitlab/exec/gitlab/project/init.py
idem_gitlab/exec/gitlab/project/member.py
idem_gitlab/exec/gitlab/project/protected_branch.py
idem_gitlab/exec/gitlab/project/protected_tag.py
idem_gitlab/exec/gitlab/project/tag.py
idem_gitlab/exec/gitlab/project/variable.py
idem_gitlab/tool/gitlab/acct.py
idem_gitlab/tool/gitlab/request.py
idem_gitlab/tool/gitlab/group/group.py
idem_gitlab/tool/gitlab/group/member.py
idem_gitlab/tool/gitlab/group/variable.py
idem_gitlab/tool/gitlab/project/branch.py
idem_gitlab/tool/gitlab/project/commit.py
idem_gitlab/tool/gitlab/project/member.py
idem_gitlab/tool/gitlab/project/project.py
idem_gitlab/tool/gitlab/project/protected_branch.py
idem_gitlab/tool/gitlab/project/protected_tag.py
idem_gitlab/tool/gitlab/project/runner.py
idem_gitlab/tool/gitlab/project/tag.py
idem_gitlab/tool/gitlab/project/variable.py
idem_gitlab-2.0.1.dist-info/LICENSE
idem_gitlab-2.0.1.dist-info/METADATA
idem_gitlab-2.0.1.dist-info/WHEEL
idem_gitlab-2.0.1.dist-info/top_level.txt
idem_gitlab-2.0.1.dist-info/RECORD
