Metadata-Version: 2.1
Name: idem-gitlab
Version: 2.0.1
Summary: Gitlab Provider plugins for Idem
Home-page: https://gitlab.com/vmware/idem/idem-gitlab
Author: VMware, Inc.
Author-email: idemproject@vmware.com
License: Apache Software License 2.0
Project-URL: Code, https://gitlab.com/vmware/idem/idem-gitlab
Project-URL: Issue tracker, https://gitlab.com/vmware/idem/idem-gitlab/issues
Classifier: Environment :: Console
Classifier: Intended Audience :: Developers
Classifier: Intended Audience :: Information Technology
Classifier: Intended Audience :: System Administrators
Classifier: Operating System :: OS Independent
Classifier: Programming Language :: Python
Classifier: Programming Language :: Python :: 3.9
Classifier: Programming Language :: Python :: 3.10
Classifier: Programming Language :: Python :: 3.11
Classifier: Development Status :: 5 - Production/Stable
Classifier: License :: OSI Approved :: Apache Software License
Requires-Python: >=3.9
License-File: LICENSE
Requires-Dist: pop >=27.0.1
Requires-Dist: pop-config >=12.0.4
Requires-Dist: idem >=24.2.2
Requires-Dist: idem-aiohttp >=3.0.1
Provides-Extra: autogen
Requires-Dist: bs4 ; extra == 'autogen'
Requires-Dist: lxml ; extra == 'autogen'
Requires-Dist: inflect ; extra == 'autogen'
Requires-Dist: parse-rest ; extra == 'autogen'
Requires-Dist: pop-create-idem >=4.4.3 ; extra == 'autogen'
Provides-Extra: full
Requires-Dist: lxml ; extra == 'full'
Requires-Dist: pop-create-idem >=4.4.3 ; extra == 'full'
Requires-Dist: inflect ; extra == 'full'
Requires-Dist: parse-rest ; extra == 'full'
Requires-Dist: bs4 ; extra == 'full'
